{
    "semester_start": "07/03/2026",
    "semester_end": "30/07/2026",
    "notify_before_mins": 15,
    "notify_after_mins": 15,
    "show_weekend": false,
    "language": "he",
    "courses": [
        {
            "course_id": "1773604326.9065745",
            "title": "אלגברה 2 ",
            "lecturer": "",
            "course_code": "",
            "link": "",
            "color": "#F9FBE7",
            "meetings": [
                {
                    "day_name": "days.wednesday",
                    "start_time": "10:00",
                    "end_time": "12:00",
                    "location": "קפלן",
                    "meeting_type": "meeting_types.lecture"
                },
                {
                    "day_name": "days.tuesday",
                    "start_time": "14:30",
                    "end_time": "16:00",
                    "location": "קפלן",
                    "meeting_type": "meeting_types.practice"
                }
            ],
            "lectures": [
                {
                    "session_id": "1773608287.13405512026-03-1014:30",
                    "title": "אלגברה 2  - תרגול",
                    "lecturer": "",
                    "date_str": "10/03/2026",
                    "start_time": "14:30",
                    "end_time": "16:00",
                    "room": "קפלן",
                    "status": "status.needs_watching",
                    "course_color": "#F9FBE7"
                },
                {
                    "session_id": "1773608287.1338682026-03-1110:00",
                    "title": "אלגברה 2  - הרצאה",
                    "lecturer": "",
                    "date_str": "11/03/2026",
                    "start_time": "10:00",
                    "end_time": "12:00",
                    "room": "קפלן",
                    "status": "status.needs_watching",
                    "course_color": "#F9FBE7"
                },
                {
                    "session_id": "1773608287.1340642026-03-1714:30",
                    "title": "אלגברה 2  - תרגול",
                    "lecturer": "",
                    "date_str": "17/03/2026",
                    "start_time": "14:30",
                    "end_time": "16:00",
                    "room": "קפלן",
                    "status": "status.needs_watching",
                    "course_color": "#F9FBE7"
                },
                {
                    "session_id": "1773608287.13389022026-03-1810:00",
                    "title": "אלגברה 2  - הרצאה",
                    "lecturer": "",
                    "date_str": "18/03/2026",
                    "start_time": "10:00",
                    "end_time": "12:00",
                    "room": "קפלן",
                    "status": "status.needs_watching",
                    "course_color": "#F9FBE7"
                },
                {
                    "session_id": "1773608287.13407182026-03-2414:30",
                    "title": "אלגברה 2  - תרגול",
                    "lecturer": "",
                    "date_str": "24/03/2026",
                    "start_time": "14:30",
                    "end_time": "16:00",
                    "room": "קפלן",
                    "status": "status.needs_watching",
                    "course_color": "#F9FBE7"
                },
                {
                    "session_id": "1773608287.13390282026-03-2510:00",
                    "title": "אלגברה 2  - הרצאה",
                    "lecturer": "",
                    "date_str": "25/03/2026",
                    "start_time": "10:00",
                    "end_time": "12:00",
                    "room": "קפלן",
                    "status": "status.needs_watching",
                    "course_color": "#F9FBE7"
                },
                {
                    "session_id": "1773608287.13407972026-03-3114:30",
                    "title": "אלגברה 2  - תרגול",
                    "lecturer": "",
                    "date_str": "31/03/2026",
                    "start_time": "14:30",
                    "end_time": "16:00",
                    "room": "קפלן",
                    "status": "status.needs_watching",
                    "course_color": "#F9FBE7"
                },
                {
                    "session_id": "1773608287.13391282026-04-0110:00",
                    "title": "אלגברה 2  - הרצאה",
                    "lecturer": "",
                    "date_str": "01/04/2026",
                    "start_time": "10:00",
                    "end_time": "12:00",
                    "room": "קפלן",
                    "status": "status.needs_watching",
                    "course_color": "#F9FBE7"
                },
                {
                    "session_id": "1773608287.13408732026-04-0714:30",
                    "title": "אלגברה 2  - תרגול",
                    "lecturer": "",
                    "date_str": "07/04/2026",
                    "start_time": "14:30",
                    "end_time": "16:00",
                    "room": "קפלן",
                    "status": "status.needs_watching",
                    "course_color": "#F9FBE7"
                },
                {
                    "session_id": "1773608287.13392192026-04-0810:00",
                    "title": "אלגברה 2  - הרצאה",
                    "lecturer": "",
                    "date_str": "08/04/2026",
                    "start_time": "10:00",
                    "end_time": "12:00",
                    "room": "קפלן",
                    "status": "status.needs_watching",
                    "course_color": "#F9FBE7"
                },
                {
                    "session_id": "1773608287.13409522026-04-1414:30",
                    "title": "אלגברה 2  - תרגול",
                    "lecturer": "",
                    "date_str": "14/04/2026",
                    "start_time": "14:30",
                    "end_time": "16:00",
                    "room": "קפלן",
                    "status": "status.needs_watching",
                    "course_color": "#F9FBE7"
                },
                {
                    "session_id": "1773608287.13393042026-04-1510:00",
                    "title": "אלגברה 2  - הרצאה",
                    "lecturer": "",
                    "date_str": "15/04/2026",
                    "start_time": "10:00",
                    "end_time": "12:00",
                    "room": "קפלן",
                    "status": "status.needs_watching",
                    "course_color": "#F9FBE7"
                },
                {
                    "session_id": "1773608287.13410282026-04-2114:30",
                    "title": "אלגברה 2  - תרגול",
                    "lecturer": "",
                    "date_str": "21/04/2026",
                    "start_time": "14:30",
                    "end_time": "16:00",
                    "room": "קפלן",
                    "status": "status.needs_watching",
                    "course_color": "#F9FBE7"
                },
                {
                    "session_id": "1773608287.13393862026-04-2210:00",
                    "title": "אלגברה 2  - הרצאה",
                    "lecturer": "",
                    "date_str": "22/04/2026",
                    "start_time": "10:00",
                    "end_time": "12:00",
                    "room": "קפלן",
                    "status": "status.needs_watching",
                    "course_color": "#F9FBE7"
                },
                {
                    "session_id": "1773608287.13411052026-04-2814:30",
                    "title": "אלגברה 2  - תרגול",
                    "lecturer": "",
                    "date_str": "28/04/2026",
                    "start_time": "14:30",
                    "end_time": "16:00",
                    "room": "קפלן",
                    "status": "status.needs_watching",
                    "course_color": "#F9FBE7"
                },
                {
                    "session_id": "1773608287.13394622026-04-2910:00",
                    "title": "אלגברה 2  - הרצאה",
                    "lecturer": "",
                    "date_str": "29/04/2026",
                    "start_time": "10:00",
                    "end_time": "12:00",
                    "room": "קפלן",
                    "status": "status.needs_watching",
                    "course_color": "#F9FBE7"
                },
                {
                    "session_id": "1773608287.13411782026-05-0514:30",
                    "title": "אלגברה 2  - תרגול",
                    "lecturer": "",
                    "date_str": "05/05/2026",
                    "start_time": "14:30",
                    "end_time": "16:00",
                    "room": "קפלן",
                    "status": "status.needs_watching",
                    "course_color": "#F9FBE7"
                },
                {
                    "session_id": "1773608287.1339542026-05-0610:00",
                    "title": "אלגברה 2  - הרצאה",
                    "lecturer": "",
                    "date_str": "06/05/2026",
                    "start_time": "10:00",
                    "end_time": "12:00",
                    "room": "קפלן",
                    "status": "status.needs_watching",
                    "course_color": "#F9FBE7"
                },
                {
                    "session_id": "1773608287.13412522026-05-1214:30",
                    "title": "אלגברה 2  - תרגול",
                    "lecturer": "",
                    "date_str": "12/05/2026",
                    "start_time": "14:30",
                    "end_time": "16:00",
                    "room": "קפלן",
                    "status": "status.needs_watching",
                    "course_color": "#F9FBE7"
                },
                {
                    "session_id": "1773608287.13396172026-05-1310:00",
                    "title": "אלגברה 2  - הרצאה",
                    "lecturer": "",
                    "date_str": "13/05/2026",
                    "start_time": "10:00",
                    "end_time": "12:00",
                    "room": "קפלן",
                    "status": "status.needs_watching",
                    "course_color": "#F9FBE7"
                },
                {
                    "session_id": "1773608287.13413262026-05-1914:30",
                    "title": "אלגברה 2  - תרגול",
                    "lecturer": "",
                    "date_str": "19/05/2026",
                    "start_time": "14:30",
                    "end_time": "16:00",
                    "room": "קפלן",
                    "status": "status.needs_watching",
                    "course_color": "#F9FBE7"
                },
                {
                    "session_id": "1773608287.13396932026-05-2010:00",
                    "title": "אלגברה 2  - הרצאה",
                    "lecturer": "",
                    "date_str": "20/05/2026",
                    "start_time": "10:00",
                    "end_time": "12:00",
                    "room": "קפלן",
                    "status": "status.needs_watching",
                    "course_color": "#F9FBE7"
                },
                {
                    "session_id": "1773608287.13414052026-05-2614:30",
                    "title": "אלגברה 2  - תרגול",
                    "lecturer": "",
                    "date_str": "26/05/2026",
                    "start_time": "14:30",
                    "end_time": "16:00",
                    "room": "קפלן",
                    "status": "status.needs_watching",
                    "course_color": "#F9FBE7"
                },
                {
                    "session_id": "1773608287.1339772026-05-2710:00",
                    "title": "אלגברה 2  - הרצאה",
                    "lecturer": "",
                    "date_str": "27/05/2026",
                    "start_time": "10:00",
                    "end_time": "12:00",
                    "room": "קפלן",
                    "status": "status.needs_watching",
                    "course_color": "#F9FBE7"
                },
                {
                    "session_id": "1773608287.13414812026-06-0214:30",
                    "title": "אלגברה 2  - תרגול",
                    "lecturer": "",
                    "date_str": "02/06/2026",
                    "start_time": "14:30",
                    "end_time": "16:00",
                    "room": "קפלן",
                    "status": "status.needs_watching",
                    "course_color": "#F9FBE7"
                },
                {
                    "session_id": "1773608287.13398462026-06-0310:00",
                    "title": "אלגברה 2  - הרצאה",
                    "lecturer": "",
                    "date_str": "03/06/2026",
                    "start_time": "10:00",
                    "end_time": "12:00",
                    "room": "קפלן",
                    "status": "status.needs_watching",
                    "course_color": "#F9FBE7"
                },
                {
                    "session_id": "1773608287.13415552026-06-0914:30",
                    "title": "אלגברה 2  - תרגול",
                    "lecturer": "",
                    "date_str": "09/06/2026",
                    "start_time": "14:30",
                    "end_time": "16:00",
                    "room": "קפלן",
                    "status": "status.needs_watching",
                    "course_color": "#F9FBE7"
                },
                {
                    "session_id": "1773608287.13399222026-06-1010:00",
                    "title": "אלגברה 2  - הרצאה",
                    "lecturer": "",
                    "date_str": "10/06/2026",
                    "start_time": "10:00",
                    "end_time": "12:00",
                    "room": "קפלן",
                    "status": "status.needs_watching",
                    "course_color": "#F9FBE7"
                },
                {
                    "session_id": "1773608287.13416312026-06-1614:30",
                    "title": "אלגברה 2  - תרגול",
                    "lecturer": "",
                    "date_str": "16/06/2026",
                    "start_time": "14:30",
                    "end_time": "16:00",
                    "room": "קפלן",
                    "status": "status.needs_watching",
                    "course_color": "#F9FBE7"
                },
                {
                    "session_id": "1773608287.13399982026-06-1710:00",
                    "title": "אלגברה 2  - הרצאה",
                    "lecturer": "",
                    "date_str": "17/06/2026",
                    "start_time": "10:00",
                    "end_time": "12:00",
                    "room": "קפלן",
                    "status": "status.needs_watching",
                    "course_color": "#F9FBE7"
                },
                {
                    "session_id": "1773608287.13417032026-06-2314:30",
                    "title": "אלגברה 2  - תרגול",
                    "lecturer": "",
                    "date_str": "23/06/2026",
                    "start_time": "14:30",
                    "end_time": "16:00",
                    "room": "קפלן",
                    "status": "status.needs_watching",
                    "course_color": "#F9FBE7"
                },
                {
                    "session_id": "1773608287.13400722026-06-2410:00",
                    "title": "אלגברה 2  - הרצאה",
                    "lecturer": "",
                    "date_str": "24/06/2026",
                    "start_time": "10:00",
                    "end_time": "12:00",
                    "room": "קפלן",
                    "status": "status.needs_watching",
                    "course_color": "#F9FBE7"
                },
                {
                    "session_id": "1773608287.13417862026-06-3014:30",
                    "title": "אלגברה 2  - תרגול",
                    "lecturer": "",
                    "date_str": "30/06/2026",
                    "start_time": "14:30",
                    "end_time": "16:00",
                    "room": "קפלן",
                    "status": "status.needs_watching",
                    "course_color": "#F9FBE7"
                },
                {
                    "session_id": "1773608287.1340152026-07-0110:00",
                    "title": "אלגברה 2  - הרצאה",
                    "lecturer": "",
                    "date_str": "01/07/2026",
                    "start_time": "10:00",
                    "end_time": "12:00",
                    "room": "קפלן",
                    "status": "status.needs_watching",
                    "course_color": "#F9FBE7"
                },
                {
                    "session_id": "1773608287.13418982026-07-0714:30",
                    "title": "אלגברה 2  - תרגול",
                    "lecturer": "",
                    "date_str": "07/07/2026",
                    "start_time": "14:30",
                    "end_time": "16:00",
                    "room": "קפלן",
                    "status": "status.needs_watching",
                    "course_color": "#F9FBE7"
                },
                {
                    "session_id": "1773608287.13402272026-07-0810:00",
                    "title": "אלגברה 2  - הרצאה",
                    "lecturer": "",
                    "date_str": "08/07/2026",
                    "start_time": "10:00",
                    "end_time": "12:00",
                    "room": "קפלן",
                    "status": "status.needs_watching",
                    "course_color": "#F9FBE7"
                },
                {
                    "session_id": "1773608287.13419752026-07-1414:30",
                    "title": "אלגברה 2  - תרגול",
                    "lecturer": "",
                    "date_str": "14/07/2026",
                    "start_time": "14:30",
                    "end_time": "16:00",
                    "room": "קפלן",
                    "status": "status.needs_watching",
                    "course_color": "#F9FBE7"
                },
                {
                    "session_id": "1773608287.134032026-07-1510:00",
                    "title": "אלגברה 2  - הרצאה",
                    "lecturer": "",
                    "date_str": "15/07/2026",
                    "start_time": "10:00",
                    "end_time": "12:00",
                    "room": "קפלן",
                    "status": "status.needs_watching",
                    "course_color": "#F9FBE7"
                },
                {
                    "session_id": "1773608287.1342052026-07-2114:30",
                    "title": "אלגברה 2  - תרגול",
                    "lecturer": "",
                    "date_str": "21/07/2026",
                    "start_time": "14:30",
                    "end_time": "16:00",
                    "room": "קפלן",
                    "status": "status.needs_watching",
                    "course_color": "#F9FBE7"
                },
                {
                    "session_id": "1773608287.13403772026-07-2210:00",
                    "title": "אלגברה 2  - הרצאה",
                    "lecturer": "",
                    "date_str": "22/07/2026",
                    "start_time": "10:00",
                    "end_time": "12:00",
                    "room": "קפלן",
                    "status": "status.needs_watching",
                    "course_color": "#F9FBE7"
                },
                {
                    "session_id": "1773608287.13421252026-07-2814:30",
                    "title": "אלגברה 2  - תרגול",
                    "lecturer": "",
                    "date_str": "28/07/2026",
                    "start_time": "14:30",
                    "end_time": "16:00",
                    "room": "קפלן",
                    "status": "status.needs_watching",
                    "course_color": "#F9FBE7"
                },
                {
                    "session_id": "1773608287.13404542026-07-2910:00",
                    "title": "אלגברה 2  - הרצאה",
                    "lecturer": "",
                    "date_str": "29/07/2026",
                    "start_time": "10:00",
                    "end_time": "12:00",
                    "room": "קפלן",
                    "status": "status.needs_watching",
                    "course_color": "#F9FBE7"
                }
            ]
        }
    ]
}